mkdocs_plantuml_local/__init__.py
mkdocs_plantuml_local/caching.py
mkdocs_plantuml_local/config.py
mkdocs_plantuml_local/dependencies.py
mkdocs_plantuml_local/hashing.py
mkdocs_plantuml_local/logging.py
mkdocs_plantuml_local/plantuml.jar
mkdocs_plantuml_local/plugin.py
mkdocs_plantuml_local/render.py
mkdocs_plantuml_local-0.5.0.dist-info/LICENSE.md
mkdocs_plantuml_local-0.5.0.dist-info/METADATA
mkdocs_plantuml_local-0.5.0.dist-info/WHEEL
mkdocs_plantuml_local-0.5.0.dist-info/entry_points.txt
mkdocs_plantuml_local-0.5.0.dist-info/RECORD
