Metadata-Version: 2.1
Name: mkdocs-plantuml-local
Version: 0.5.0
Summary: Render PlantUML diagrams without sending sensitive data to a public server
Home-page: https://github.com/acodeninja/mkdocs-plantuml-local
License: MIT
Author: Lawrence
Author-email: lawrence@acode.ninja
Requires-Python: >=3.9
Classifier: License :: OSI Approved :: MIT License
Classifier: Programming Language :: Python :: 3
Classifier: Programming Language :: Python :: 3.9
Classifier: Programming Language :: Python :: 3.10
Classifier: Programming Language :: Python :: 3.11
Classifier: Programming Language :: Python :: 3.12
Requires-Dist: cssselect (>=1.2.0,<2.0.0)
Requires-Dist: lxml (>=5.1.0,<6.0.0)
Requires-Dist: mkdocs (>=1.4.3)
Requires-Dist: pymdown-extensions (>=10.7,<11.0)
